yabs_test/__init__.py
yabs_test/cli.py
yabs_test-0.2.8.dist-info/LICENSE.txt
yabs_test-0.2.8.dist-info/METADATA
yabs_test-0.2.8.dist-info/WHEEL
yabs_test-0.2.8.dist-info/entry_points.txt
yabs_test-0.2.8.dist-info/top_level.txt
yabs_test-0.2.8.dist-info/RECORD
