Metadata-Version: 2.1
Name: yabs-test
Version: 0.2.8
Summary: Dummy application to release workflows with mar10/yabs
Home-page: https://github.com/mar10/yabs-test
Author: Martin Wendt
Author-email: yabs@wwwendt.de
Maintainer: Martin Wendt
Maintainer-email: yabs@wwwendt.de
License: MIT
Keywords: test,temporary,setup,yabs
Platform: UNKNOWN
Classifier: Development Status :: 1 - Planning
Classifier: Environment :: Console
Classifier: Intended Audience :: Developers
Classifier: License :: OSI Approved :: MIT License
Classifier: Operating System :: OS Independent
Classifier: Programming Language :: Python
Classifier: Programming Language :: Python :: 3
Classifier: Programming Language :: Python :: 3.7
Classifier: Programming Language :: Python :: 3.8
Classifier: Programming Language :: Python :: 3.9
Classifier: Programming Language :: Python :: 3.10
Classifier: Topic :: Software Development :: Testing
License-File: LICENSE.txt
